eisplottingtool/EISFrame.py
eisplottingtool/EISFrameOld.py
eisplottingtool/__init__.py
eisplottingtool/parser/CircuitComponents.py
eisplottingtool/parser/CircuitParser.py
eisplottingtool/parser/SchemeElements.py
eisplottingtool/parser/__init__.py
eisplottingtool/process/__init__.py
eisplottingtool/process/circuit.py
eisplottingtool/process/trends.py
eisplottingtool/utils/MarkPoints.py
eisplottingtool/utils/Parameter.py
eisplottingtool/utils/UtilFunctions.py
eisplottingtool/utils/__init__.py
eisplottingtool/utils/fitting.py
eisplottingtool/visualize/CircuitPlotter.py
eisplottingtool/visualize/SchematicDrawer.py
eisplottingtool/visualize/__init__.py
eisplottingtool-0.1.5.dist-info/LICENSE
eisplottingtool-0.1.5.dist-info/METADATA
eisplottingtool-0.1.5.dist-info/WHEEL
eisplottingtool-0.1.5.dist-info/top_level.txt
eisplottingtool-0.1.5.dist-info/RECORD
