Metadata-Version: 2.1
Name: eisplottingtool
Version: 0.1.5
Summary: A tool used to plot EIS data and other battery related data
Home-page: https://github.com/ileu/EISFrame
Author: Ulrich Sauter
Author-email: usauterv@outlook.com
License: UNKNOWN
Project-URL: Bug Tracker, https://github.com/ileu/EISFrame/issues
Platform: UNKNOWN
Classifier: Intended Audience :: Science/Research
Classifier: Programming Language :: Python :: 3
Classifier: License :: OSI Approved :: GNU General Public License v3 or later (GPLv3+)
Classifier: Operating System :: OS Independent
Classifier: Topic :: Scientific/Engineering :: Chemistry
Requires-Python: >=3.9
License-File: LICENSE
Requires-Dist: numpy
Requires-Dist: pandas
Requires-Dist: eclabfiles (>=0.4.0)
Requires-Dist: pint
Requires-Dist: scipy
Requires-Dist: matplotlib
Requires-Dist: schemdraw (>=0.12)
